dftracer/analyzer/__init__.py
dftracer/analyzer/__main__.py
dftracer/analyzer/_version.py
dftracer/analyzer/analysis.py
dftracer/analyzer/analysis_utils.py
dftracer/analyzer/analyzer.py
dftracer/analyzer/cluster.py
dftracer/analyzer/config.py
dftracer/analyzer/constants.py
dftracer/analyzer/darshan.py
dftracer/analyzer/dftracer.py
dftracer/analyzer/metrics.py
dftracer/analyzer/output.py
dftracer/analyzer/recorder.py
dftracer/analyzer/types.py
dftracer/analyzer/utils/__init__.py
dftracer/analyzer/utils/collection_utils.py
dftracer/analyzer/utils/common_utils.py
dftracer/analyzer/utils/dask_agg.py
dftracer/analyzer/utils/dask_utils.py
dftracer/analyzer/utils/distributed_plugins.py
dftracer/analyzer/utils/env_utils.py
dftracer/analyzer/utils/expr_utils.py
dftracer/analyzer/utils/file_utils.py
dftracer/analyzer/utils/json_encoders.py
dftracer/analyzer/utils/log_utils.py
dftracer/analyzer/utils/notebook_utils.py
dftracer/analyzer/utils/warning_utils.py
dftracer_analyzer-0.0.6.data/scripts/dftracer-analyzer-recorder2parquet
dftracer_analyzer.libs/libarrow-a446d91d.so.2200.0.0
dftracer_analyzer.libs/libbrotlicommon-abf86ae9.so.1.0.9
dftracer_analyzer.libs/libbrotlidec-db9dbda7.so.1.0.9
dftracer_analyzer.libs/libbrotlienc-b88bfc46.so.1.0.9
dftracer_analyzer.libs/libbz2-5e516f77.so.1.0.4
dftracer_analyzer.libs/libcom_err-f196091d.so.2.1
dftracer_analyzer.libs/libcrypto-ef58def3.so.3
dftracer_analyzer.libs/libcurl-ef05c8ea.so.4.7.0
dftracer_analyzer.libs/libevent_core-2-0b7a5ee5.1.so.7.0.1
dftracer_analyzer.libs/libevent_pthreads-2-ad95e3c1.1.so.7.0.1
dftracer_analyzer.libs/libffi-247da4d5.so.8.1.0
dftracer_analyzer.libs/libgmp-4dc20a90.so.10.4.1
dftracer_analyzer.libs/libgnutls-a1c10edc.so.30.31.0
dftracer_analyzer.libs/libgssapi_krb5-74c938dc.so.2.2
dftracer_analyzer.libs/libhogweed-47d56894.so.6.4
dftracer_analyzer.libs/libhwloc-2efe6e32.so.15.5.2
dftracer_analyzer.libs/libicudata-c1404396.so.70.1
dftracer_analyzer-0.0.6.dist-info/METADATA
dftracer_analyzer-0.0.6.dist-info/WHEEL
dftracer_analyzer-0.0.6.dist-info/entry_points.txt
dftracer_analyzer-0.0.6.dist-info/RECORD
dftracer_analyzer-0.0.6.dist-info/sboms/auditwheel.cdx.json
