Metadata-Version: 2.1
Name: dftracer-analyzer
Version: 0.0.6
Summary: Analyze, visualize, and understand I/O performance issues in HPC workflows
Author-Email: Izzet Yildirim <izzetcyildirim@gmail.com>
Maintainer-Email: Izzet Yildirim <izzetcyildirim@gmail.com>
Classifier: Development Status :: 3 - Alpha
Classifier: Intended Audience :: Science/Research
Classifier: License :: OSI Approved :: MIT License
Classifier: Programming Language :: Python
Classifier: Programming Language :: Python :: 3
Classifier: Programming Language :: Python :: 3.9
Classifier: Programming Language :: Python :: 3.10
Classifier: Programming Language :: Python :: 3.11
Classifier: Programming Language :: Python :: 3.12
Classifier: Programming Language :: Python :: 3 :: Only
Classifier: Topic :: Scientific/Engineering
Classifier: Topic :: Software Development :: Build Tools
Classifier: Typing :: Typed
Project-URL: documentation, https://dfanalyzer.readthedocs.io/en/latest/
Project-URL: source, https://github.com/LLNL/dfanalyzer
Project-URL: tracker, https://github.com/LLNL/dfanalyzer/issues
Requires-Python: <3.13,>3.8
Requires-Dist: betterset>=0.1.0
Requires-Dist: dask[bag,dataframe,distributed]<2025,>=2024.1.0
Requires-Dist: dask_jobqueue>=0.8.0
Requires-Dist: hydra-core~=1.3.0
Requires-Dist: inflect==7.0
Requires-Dist: numpy>=2.0.0
Requires-Dist: pandas>=2.2.0
Requires-Dist: portion>=2.4.0
Requires-Dist: pyarrow>=13
Requires-Dist: rich~=14.1.0
Requires-Dist: strenum>=0.4
Requires-Dist: structlog>=25
Requires-Dist: dftracer-utils>=0.0.5
Provides-Extra: darshan
Requires-Dist: darshan>=3.4; extra == "darshan"
